mangoautomation/__init__.py
mangoautomation/enums/__init__.py
mangoautomation/enums/_base_enum.py
mangoautomation/enums/_ui_enum.py
mangoautomation/exceptions/__init__.py
mangoautomation/exceptions/_exceptions.py
mangoautomation/exceptions/error_msg.py
mangoautomation/mangos/__init__.py
mangoautomation/mangos/mangos.cp310-win_amd64.pyd
mangoautomation/mangos/mangos.cp312-win_amd64.pyd
mangoautomation/mangos/mangos.cpython-310-darwin.so
mangoautomation/mangos/mangos.cpython-310-x86_64-linux-gnu.so
mangoautomation/mangos/mangos.cpython-312-darwin.so
mangoautomation/mangos/mangos.cpython-312-x86_64-linux-gnu.so
mangoautomation/models/__init__.py
mangoautomation/models/_ui_model.py
mangoautomation/tools/__init__.py
mangoautomation/tools/_mate.py
mangoautomation/tools/_uiautodev.py
mangoautomation/uidrive/__init__.py
mangoautomation/uidrives/__init__.py
mangoautomation/uidrives/_async_element.py
mangoautomation/uidrives/_base_data.py
mangoautomation/uidrives/_driver_object.py
mangoautomation/uidrives/_sync_element.py
mangoautomation/uidrives/android/__init__.py
mangoautomation/uidrives/ios/__init__.py
mangoautomation/uidrives/pc/__init__.py
mangoautomation/uidrives/pc/assertion.py
mangoautomation/uidrives/pc/customization.py
mangoautomation/uidrives/pc/element.py
mangoautomation/uidrives/pc/input_device.py
mangoautomation/uidrives/pc/new_windows.py
mangoautomation/uidrives/web/__init__.py
mangoautomation/uidrives/web/_async_web.py
mangoautomation/uidrives/web/_sync_web.py
mangoautomation-1.1.38.dist-info/licenses/LICENSE
tests/__init__.py
tests/get_ope.py
tests/test_ai_element.py
tests/test_html.py
tests/test_ui_and.py
tests/test_ui_web.py
tests/test_ui_web_sync.py
tests/test_uimango.py
mangoautomation-1.1.38.dist-info/METADATA
mangoautomation-1.1.38.dist-info/WHEEL
mangoautomation-1.1.38.dist-info/top_level.txt
mangoautomation-1.1.38.dist-info/RECORD
