Metadata-Version: 2.4
Name: mangoautomation
Version: 1.1.38
Summary: 测试工具
Home-page: https://gitee.com/mao-peng/testkit
Author: 毛鹏
Author-email: 729164035@qq.com
Classifier: Programming Language :: Python :: 3.10
Classifier: Programming Language :: Python :: 3.12
License-File: LICENSE
Requires-Dist: pydantic>=2.9.2
Requires-Dist: playwright==1.43.0
Requires-Dist: uiautomation>=2.0.20
Requires-Dist: uiautomator2>=3.2.5
Requires-Dist: mangotools>=1.1.61
Requires-Dist: adbutils~=2.8.9
Requires-Dist: uiautodev>=0.9.0
Requires-Dist: beautifulsoup4==4.14.2
Requires-Dist: openai==2.6.1
Dynamic: author
Dynamic: author-email
Dynamic: classifier
Dynamic: description
Dynamic: description-content-type
Dynamic: home-page
Dynamic: license-file
Dynamic: requires-dist
Dynamic: summary
